langchain_valthera/__init__.py
langchain_valthera/py.typed
langchain_valthera/tools.py
langchain_valthera-0.1.3.dist-info/LICENSE
langchain_valthera-0.1.3.dist-info/METADATA
langchain_valthera-0.1.3.dist-info/WHEEL
langchain_valthera-0.1.3.dist-info/RECORD
