Metadata-Version: 2.1
Name: langchain-valthera
Version: 0.1.3
Summary: An integration package connecting Valthera and LangChain
Home-page: https://github.com/valthera/langchain-valthera
License: MIT
Requires-Python: >=3.9,<4.0
Classifier: License :: OSI Approved :: MIT License
Classifier: Programming Language :: Python :: 3
Classifier: Programming Language :: Python :: 3.9
Classifier: Programming Language :: Python :: 3.10
Classifier: Programming Language :: Python :: 3.11
Classifier: Programming Language :: Python :: 3.12
Classifier: Programming Language :: Python :: 3.13
Requires-Dist: langchain-core (>=0.3.15,<0.4.0)
Requires-Dist: langchain-openai (>=0.3.7,<0.4.0)
Requires-Dist: langchain-tests (>=0.3.12,<0.4.0)
Requires-Dist: openai (>=1.65.2,<2.0.0)
Requires-Dist: pytest (>=8.3.5,<9.0.0)
Requires-Dist: valthera (>=0.1.2,<0.2.0)
Project-URL: Repository, https://github.com/valthera/langchain-valthera
Project-URL: Release Notes, https://github.com/valthera/langchain-valthera/releases
Project-URL: Source Code, https://github.com/valthera/langchain-valthera
